Metadata-Version: 2.1
Name: is-odd-ST
Version: 0.1
Summary: is odd number
Home-page: http://example.com
License: UNKNOWN
Platform: UNKNOWN
